setup.py
distribution_function/Binomialdistribution.py
distribution_function/Gaussiandistribution.py
distribution_function/Generaldistribution.py
distribution_function/__init__.py
distribution_function.egg-info/PKG-INFO
distribution_function.egg-info/SOURCES.txt
distribution_function.egg-info/dependency_links.txt
distribution_function.egg-info/not-zip-safe
distribution_function.egg-info/top_level.txt