Metadata-Version: 1.0
Name: distribution-function
Version: 0.1
Summary: Gaussian distributions
Home-page: UNKNOWN
Author: Dawit Teklay
Author-email: dandebrhan2@gmail.com
License: UNKNOWN
Platform: UNKNOWN
